PREDICT/CalcFeatures.py
PREDICT/__init__.py
PREDICT/addexceptions.py
PREDICT/IOparser/__init__.py
PREDICT/IOparser/config_io.py
PREDICT/IOparser/config_io_CalcFeatures.py
PREDICT/IOparser/file_io.py
PREDICT/helpers/__init__.py
PREDICT/helpers/contour_functions.py
PREDICT/helpers/contour_functions_3d.py
PREDICT/helpers/image_helper.py
PREDICT/helpers/orientation_functions.py
PREDICT/helpers/sitk_helper.py
PREDICT/imagefeatures/__init__.py
PREDICT/imagefeatures/coliage_features.py
PREDICT/imagefeatures/contour_functions.py
PREDICT/imagefeatures/dicom_features.py
PREDICT/imagefeatures/dti_features.py
PREDICT/imagefeatures/get_features.py
PREDICT/imagefeatures/histogram_features.py
PREDICT/imagefeatures/image_helper.py
PREDICT/imagefeatures/log_features.py
PREDICT/imagefeatures/orientation_features.py
PREDICT/imagefeatures/phase_features.py
PREDICT/imagefeatures/semantic_features.py
PREDICT/imagefeatures/shape_features.py
PREDICT/imagefeatures/sitk_helper.py
PREDICT/imagefeatures/texture_features.py
PREDICT/imagefeatures/vessel_features.py
PREDICT/plotting/__init__.py
PREDICT/plotting/getfeatureimages.py
docs/conf.py
docs/_build/html/.buildinfo
docs/_build/html/PREDICT.IOparser.html
docs/_build/html/PREDICT.helpers.html
docs/_build/html/PREDICT.html
docs/_build/html/PREDICT.imagefeatures.html
docs/_build/html/PREDICT.plotting.html
docs/_build/html/genindex.html
docs/_build/html/index.html
docs/_build/html/modules.html
docs/_build/html/objects.inv
docs/_build/html/search.html
docs/_build/html/searchindex.js
docs/_build/html/_sources/PREDICT.IOparser.rst.txt
docs/_build/html/_sources/PREDICT.helpers.rst.txt
docs/_build/html/_sources/PREDICT.imagefeatures.rst.txt
docs/_build/html/_sources/PREDICT.plotting.rst.txt
docs/_build/html/_sources/PREDICT.rst.txt
docs/_build/html/_sources/index.rst.txt
docs/_build/html/_sources/modules.rst.txt
docs/_build/html/_static/alabaster.css
docs/_build/html/_static/basic.css
docs/_build/html/_static/custom.css
predict-3.2.0.dist-info/licenses/LICENSE
predict-3.2.0.dist-info/METADATA
predict-3.2.0.dist-info/WHEEL
predict-3.2.0.dist-info/entry_points.txt
predict-3.2.0.dist-info/top_level.txt
predict-3.2.0.dist-info/RECORD
