Metadata-Version: 2.4
Name: PREDICT
Version: 3.2.0
Summary: Predict: a Radiomics Extensive Digital Interchangable Classification Toolkit.
Author-email: "Martijn P. A. Starmans" <m.starmans@erasmusmc.nl>, "Sebastian R. van der Voort" <s.vandervoort@erasmusmc.nl>
License-Expression: Apache-2.0
Project-URL: Homepage, https://github.com/Svdvoort/PREDICTFastr
Keywords: bioinformatics,radiomics,features
Classifier: Development Status :: 5 - Production/Stable
Classifier: Intended Audience :: Developers
Classifier: Intended Audience :: Science/Research
Classifier: Intended Audience :: Healthcare Industry
Classifier: Intended Audience :: Information Technology
Classifier: Intended Audience :: Education
Classifier: Natural Language :: English
Classifier: Operating System :: OS Independent
Classifier: Programming Language :: Python :: 3.11
Classifier: Programming Language :: Python :: 3 :: Only
Classifier: Topic :: Scientific/Engineering :: Information Analysis
Classifier: Topic :: System :: Distributed Computing
Classifier: Topic :: System :: Logging
Classifier: Topic :: Utilities
Requires-Python: >=3.11
License-File: LICENSE
Requires-Dist: numpy==1.26.3
Requires-Dist: configparser
Requires-Dist: joblib
Requires-Dist: natsort
Requires-Dist: pandas
Requires-Dist: phasepack
Requires-Dist: pyradiomics==3.0.1
Requires-Dist: scipy
Requires-Dist: scikit-image
Requires-Dist: SimpleITK
Requires-Dist: tables
Requires-Dist: pydicom
Dynamic: license-file
